{
  "name": "单继承",
  "node_id": "py_single_inherit_v4",
  "parent_id": "py_inherit_v4",
  "level": 8,
  "is_leaf": true,
  "absorption_rate": 0.2,
  "version": 1,
  "parent": "继承与多态",
  "children": [],
  "vector_file": "vector.txt",
  "metadata": {},
  "data_pointers": [
    {
      "title": "单继承",
      "uri": "knowledge://py_single_inherit_v4",
      "content_preview": "Translation: Class B(A): Class B inherits from A. `super().__init__()` calls the constructor of the parent class. `isinstance` is used for type checking. Python code example: ```python class A: def __"
    }
  ],
  "related_nodes": []
}