{
  "name": "Kruskal 最小生成树",
  "node_id": "kruskal_v4",
  "parent_id": "graph_algo_v4",
  "level": 6,
  "is_leaf": true,
  "absorption_rate": 0.2,
  "version": 1,
  "parent": "图算法",
  "children": [],
  "vector_file": "vector.txt",
  "metadata": {},
  "data_pointers": [
    {
      "title": "Kruskal 最小生成树",
      "uri": "knowledge://kruskal_v4",
      "content_preview": "Translate the Chinese technical text to English: \"Sort edges by their weights and add them in that order as long as they do not form a cycle. Use Union-Find (or Disjoint Set Union, DSU) to detect cycl"
    }
  ],
  "related_nodes": []
}